{
    "作者": "cally",
    "站名": "白嫖影视",
    "主页url": "https://www.baipiaoys.com:9092/",
    "分类url": "https://www.baipiaoys.com:9092/show/area/{area}/by/{by}/class/{class}/id/{cateId}/lang/{lang}/page/{catePg}/year/{year}.html;;ax",
    "分类二次截取": "type-slide\">&&</ul>",
    "分类数组": "<li>&&</li>",
    "分类标题": ">&&</a>[不包含:首页]",
    "分类ID": "id/&&.html",
    "影片类型": "类型：&&<span",
    "影片年代": "年份：&&</a>",
    "影片地区": "地区：&&</a>",
    "影片状态": "text-right\">&&<",
    "导演": "导演：&&</p>",
    "主演": "主演：&&</p>",
    "简介": "(Cally)提醒您请勿相信影片中的广告，以免上当受骗！+col-pd\">&&</p>",
    "线路数组": "<h3&&</h3>",
    "线路标题": ">&&[替换:白嫖播放器>>在线播放]",
    "排序": "时间$time#人气$hits#评分$score"
}